xlsform_filler_data/__init__.py
xlsform_filler_data/xlsform_filler_data.py
xlsform_filler_data-0.1.2.dist-info/WHEEL
xlsform_filler_data-0.1.2.dist-info/entry_points.txt
xlsform_filler_data-0.1.2.dist-info/METADATA
xlsform_filler_data-0.1.2.dist-info/RECORD
