Metadata-Version: 2.1
Name: xlsform-filler-data
Version: 0.1.2
Summary: A tool for generating fake testing data based on an XLSform. 
Author: Brian Mc Donald
Author-email: brian@brianmcdonald.me
Requires-Python: >=3.8,<4.0
Classifier: Programming Language :: Python :: 3
Classifier: Programming Language :: Python :: 3.8
Classifier: Programming Language :: Python :: 3.9
Classifier: Programming Language :: Python :: 3.10
Classifier: Programming Language :: Python :: 3.11
Requires-Dist: click (>=8.1.3,<9.0.0)
Requires-Dist: lorem-text (>=2.1,<3.0)
Requires-Dist: openpyxl (>=3.1.2,<4.0.0)
Requires-Dist: pandas (>=2.0.0,<3.0.0)
